bbtq/__init__.py
bbtq/cli.py
bbtq/core.py
bbtq/tests/deep.toml
bbtq/tests/simple.toml
bbtq/tests/test.toml
bbtq/tests/test_cli.py
bbtq/tests/test_core.py
bbtq-3.0.1.dist-info/entry_points.txt
bbtq-3.0.1.dist-info/LICENSE
bbtq-3.0.1.dist-info/WHEEL
bbtq-3.0.1.dist-info/METADATA
bbtq-3.0.1.dist-info/RECORD
