Metadata-Version: 2.1
Name: bbtq
Version: 3.0.1
Summary: Barebones TOML query.
Author: Andrew Erickson
Author-email: aerickson@gmail.com
Requires-Python: >=3.7,<4.0
Classifier: Programming Language :: Python :: 3
Classifier: Programming Language :: Python :: 3.7
Classifier: Programming Language :: Python :: 3.8
Classifier: Programming Language :: Python :: 3.9
Classifier: Programming Language :: Python :: 3.10
Requires-Dist: toml (>=0.10.0,<0.11.0)
